ShujujiegouJiaochengCYuyanBianchengWang/README.md
ShujujiegouJiaochengCYuyanBianchengWang/__init__.py
ShujujiegouJiaochengCYuyanBianchengWang/__main__.py
ShujujiegouJiaochengCYuyanBianchengWang/file.epub
ShujujiegouJiaochengCYuyanBianchengWang/index.html
ShujujiegouJiaochengCYuyanBianchengWang/css/__init__.py
ShujujiegouJiaochengCYuyanBianchengWang/css/annotations.css
ShujujiegouJiaochengCYuyanBianchengWang/css/main.css
ShujujiegouJiaochengCYuyanBianchengWang/css/normalize.css
ShujujiegouJiaochengCYuyanBianchengWang/css/popup.css
ShujujiegouJiaochengCYuyanBianchengWang/font/__init__.py
ShujujiegouJiaochengCYuyanBianchengWang/font/fontello.eot
ShujujiegouJiaochengCYuyanBianchengWang/font/fontello.svg
ShujujiegouJiaochengCYuyanBianchengWang/font/fontello.ttf
ShujujiegouJiaochengCYuyanBianchengWang/font/fontello.woff
ShujujiegouJiaochengCYuyanBianchengWang/img/__init__.py
ShujujiegouJiaochengCYuyanBianchengWang/img/annotator-glyph-sprite.png
ShujujiegouJiaochengCYuyanBianchengWang/img/annotator-icon-sprite.png
ShujujiegouJiaochengCYuyanBianchengWang/img/apple-touch-icon.png
ShujujiegouJiaochengCYuyanBianchengWang/img/cancelfullscreen.png
ShujujiegouJiaochengCYuyanBianchengWang/img/close.png
ShujujiegouJiaochengCYuyanBianchengWang/img/fullscreen.png
ShujujiegouJiaochengCYuyanBianchengWang/img/loader.gif
ShujujiegouJiaochengCYuyanBianchengWang/img/menu-icon.png
ShujujiegouJiaochengCYuyanBianchengWang/img/save.png
ShujujiegouJiaochengCYuyanBianchengWang/img/saved.png
ShujujiegouJiaochengCYuyanBianchengWang/img/settings-s.png
ShujujiegouJiaochengCYuyanBianchengWang/img/settings.png
ShujujiegouJiaochengCYuyanBianchengWang/img/star.png
ShujujiegouJiaochengCYuyanBianchengWang/js/__init__.py
ShujujiegouJiaochengCYuyanBianchengWang/js/epub.js
ShujujiegouJiaochengCYuyanBianchengWang/js/epub.min.js
ShujujiegouJiaochengCYuyanBianchengWang/js/epub.min.map
ShujujiegouJiaochengCYuyanBianchengWang/js/hooks.min.js
ShujujiegouJiaochengCYuyanBianchengWang/js/hooks.min.map
shujujiegou_jiaocheng_c_yuyan_biancheng_wang-2024.3.2.0.dist-info/METADATA
shujujiegou_jiaocheng_c_yuyan_biancheng_wang-2024.3.2.0.dist-info/WHEEL
shujujiegou_jiaocheng_c_yuyan_biancheng_wang-2024.3.2.0.dist-info/entry_points.txt
shujujiegou_jiaocheng_c_yuyan_biancheng_wang-2024.3.2.0.dist-info/top_level.txt
shujujiegou_jiaocheng_c_yuyan_biancheng_wang-2024.3.2.0.dist-info/RECORD
